main.py
uv_example-0.1.0.dist-info/METADATA
uv_example-0.1.0.dist-info/WHEEL
uv_example-0.1.0.dist-info/top_level.txt
uv_example-0.1.0.dist-info/RECORD
