Metadata-Version: 2.4
Name: uv-example
Version: 0.1.0
Summary: Add your description here
Requires-Python: >=3.13
Requires-Dist: awslabs-aws-documentation-mcp-server>=0.1.2
Requires-Dist: boto3>=1.38.0
Requires-Dist: eb-mcp>=0.1.0
Requires-Dist: requests>=2.32.3
